ArticutAPI_Taigi/ArticutAPI_Taigi.py
ArticutAPI_Taigi/TL_working.py
ArticutAPI_Taigi/__init__.py
ArticutAPI_Taigi/posShift.py
ArticutAPI_Taigi/defaultDict/Taigi_Lexicon.py
ArticutAPI_Taigi/defaultDict/__init__.py
ArticutAPI_Taigi/defaultDict/DroidtownTG_dict/ACTION_eventQuantifier.py
ArticutAPI_Taigi/defaultDict/DroidtownTG_dict/ACTION_lightVerb.py
ArticutAPI_Taigi/defaultDict/DroidtownTG_dict/ACTION_quantifiedVerb.py
ArticutAPI_Taigi/defaultDict/DroidtownTG_dict/ACTION_verb.py
ArticutAPI_Taigi/defaultDict/DroidtownTG_dict/ASPECT.py
ArticutAPI_Taigi/defaultDict/DroidtownTG_dict/AUX.py
ArticutAPI_Taigi/defaultDict/DroidtownTG_dict/CLAUSE_Q.py
ArticutAPI_Taigi/defaultDict/DroidtownTG_dict/CLAUSE_particle.py
ArticutAPI_Taigi/defaultDict/DroidtownTG_dict/ENTITY_DetPhrase.py
ArticutAPI_Taigi/defaultDict/DroidtownTG_dict/ENTITY_classifier.py
ArticutAPI_Taigi/defaultDict/DroidtownTG_dict/ENTITY_measurement.py
ArticutAPI_Taigi/defaultDict/DroidtownTG_dict/ENTITY_noun.py
ArticutAPI_Taigi/defaultDict/DroidtownTG_dict/ENTITY_num.py
ArticutAPI_Taigi/defaultDict/DroidtownTG_dict/ENTITY_person.py
ArticutAPI_Taigi/defaultDict/DroidtownTG_dict/ENTITY_possessive.py
ArticutAPI_Taigi/defaultDict/DroidtownTG_dict/ENTITY_pronoun.py
ArticutAPI_Taigi/defaultDict/DroidtownTG_dict/FUNC_conjunction.py
ArticutAPI_Taigi/defaultDict/DroidtownTG_dict/FUNC_degreeHead.py
ArticutAPI_Taigi/defaultDict/DroidtownTG_dict/FUNC_inner.py
ArticutAPI_Taigi/defaultDict/DroidtownTG_dict/FUNC_inter.py
ArticutAPI_Taigi/defaultDict/DroidtownTG_dict/FUNC_negation.py
ArticutAPI_Taigi/defaultDict/DroidtownTG_dict/IDIOM.py
ArticutAPI_Taigi/defaultDict/DroidtownTG_dict/LOCATION.py
ArticutAPI_Taigi/defaultDict/DroidtownTG_dict/MODAL.py
ArticutAPI_Taigi/defaultDict/DroidtownTG_dict/MODIFIER.py
ArticutAPI_Taigi/defaultDict/DroidtownTG_dict/MODIFIER_color.py
ArticutAPI_Taigi/defaultDict/DroidtownTG_dict/QUANTIFIER.py
ArticutAPI_Taigi/defaultDict/DroidtownTG_dict/RANGE_locality.py
ArticutAPI_Taigi-0.95.dist-info/METADATA
ArticutAPI_Taigi-0.95.dist-info/WHEEL
ArticutAPI_Taigi-0.95.dist-info/top_level.txt
ArticutAPI_Taigi-0.95.dist-info/RECORD
