Metadata-Version: 2.1
Name: ArticutAPI-Taigi
Version: 0.95
Summary: Articut NLP system provides not only finest results on Chinese word segmentaion (CWS), Part-of-Speech tagging (POS) and Named Entity Recogintion tagging (NER), but also the fastest online API service in the NLP industry.
Home-page: https://github.com/Droidtown/ArticutAPI_Taigi
Author: Droidtown Linguistic Tech. Co. Ltd.
Author-email: info@droidtown.co
License: MIT License
Project-URL: Documentation, https://api.droidtown.co/ArticutAPI/document/
Project-URL: Source, https://github.com/Droidtown/ArticutAPI
Keywords: NLP,NLU,CWS,POS,NER,AI,artificial intelligence,Chinese word segmentation,computational linguistics,language,linguistics,graphQL,natural language,natural language processing,natural language understanding,parsing,part-of-speech-embdding,part-of-speech-tagger,pos-tagger,pos-tagging,syntax,tagging,text analytics
Classifier: Programming Language :: Python :: 3
Classifier: Programming Language :: Python :: 3 :: Only
Classifier: Programming Language :: Python :: 3.6
Classifier: Programming Language :: Python :: 3.7
Classifier: Programming Language :: Python :: 3.8
Classifier: Programming Language :: Python :: 3.9
Classifier: Programming Language :: Python :: 3.10
Classifier: License :: OSI Approved :: MIT License
Classifier: Operating System :: OS Independent
Classifier: Development Status :: 5 - Production/Stable
Classifier: Intended Audience :: Developers
Classifier: Intended Audience :: Customer Service
Classifier: Intended Audience :: Information Technology
Classifier: Natural Language :: Chinese (Traditional)
Classifier: Topic :: Software Development :: Libraries :: Python Modules
Classifier: Topic :: Text Processing
Classifier: Topic :: Text Processing :: Linguistic
Classifier: Topic :: Text Processing :: Markup :: XML
Classifier: Topic :: Text Processing :: Filters
Classifier: Topic :: Utilities
Requires-Python: >=3.6.1
Requires-Dist: requests >=2.25.1
Requires-Dist: ArticutAPI
